llm_converter/__init__.py
llm_converter/cli.py
llm_converter/config.py
llm_converter/converter.py
llm_converter/exceptions.py
llm_converter/result.py
llm_converter/pipeline/__init__.py
llm_converter/pipeline/layout_detector.py
llm_converter/pipeline/model_downloader.py
llm_converter/pipeline/nanonets_processor.py
llm_converter/pipeline/neural_document_processor.py
llm_converter/pipeline/ocr_service.py
llm_converter/processors/__init__.py
llm_converter/processors/base.py
llm_converter/processors/cloud_processor.py
llm_converter/processors/docx_processor.py
llm_converter/processors/excel_processor.py
llm_converter/processors/gpu_processor.py
llm_converter/processors/html_processor.py
llm_converter/processors/image_processor.py
llm_converter/processors/pdf_processor.py
llm_converter/processors/pptx_processor.py
llm_converter/processors/txt_processor.py
llm_converter/processors/url_processor.py
llm_converter/services/__init__.py
llm_converter/services/ollama_service.py
llm_converter/utils/__init__.py
llm_converter/utils/gpu_utils.py
llm_data_converter-2.2.0.dist-info/METADATA
llm_data_converter-2.2.0.dist-info/WHEEL
llm_data_converter-2.2.0.dist-info/entry_points.txt
llm_data_converter-2.2.0.dist-info/licenses/LICENSE
llm_data_converter-2.2.0.dist-info/RECORD
